rust_dwarf-0.1.1.dist-info/METADATA
rust_dwarf-0.1.1.dist-info/WHEEL
rust_dwarf/__init__.py
rust_dwarf/rust_dwarf.cp39-win_amd64.pyd
rust_dwarf-0.1.1.dist-info/RECORD
