Metadata-Version: 2.1
Name: rust_dwarf
Version: 0.1.1
